odoo9_addon_account_mass_reconcile-9.0.1.0.0.99.dev115-py3.8-nspkg.pth
odoo_addons/account_mass_reconcile/README.rst
odoo_addons/account_mass_reconcile/__init__.py
odoo_addons/account_mass_reconcile/__openerp__.py
odoo_addons/account_mass_reconcile/i18n/account_mass_reconcile.pot
odoo_addons/account_mass_reconcile/i18n/am.po
odoo_addons/account_mass_reconcile/i18n/ar.po
odoo_addons/account_mass_reconcile/i18n/bg.po
odoo_addons/account_mass_reconcile/i18n/bs.po
odoo_addons/account_mass_reconcile/i18n/ca.po
odoo_addons/account_mass_reconcile/i18n/ca_ES.po
odoo_addons/account_mass_reconcile/i18n/cs.po
odoo_addons/account_mass_reconcile/i18n/da.po
odoo_addons/account_mass_reconcile/i18n/da_DK.po
odoo_addons/account_mass_reconcile/i18n/de.po
odoo_addons/account_mass_reconcile/i18n/el_GR.po
odoo_addons/account_mass_reconcile/i18n/en_GB.po
odoo_addons/account_mass_reconcile/i18n/es.po
odoo_addons/account_mass_reconcile/i18n/es_AR.po
odoo_addons/account_mass_reconcile/i18n/es_CL.po
odoo_addons/account_mass_reconcile/i18n/es_CO.po
odoo_addons/account_mass_reconcile/i18n/es_CR.po
odoo_addons/account_mass_reconcile/i18n/es_DO.po
odoo_addons/account_mass_reconcile/i18n/es_EC.po
odoo_addons/account_mass_reconcile/i18n/es_ES.po
odoo_addons/account_mass_reconcile/i18n/es_MX.po
odoo_addons/account_mass_reconcile/i18n/es_PE.po
odoo_addons/account_mass_reconcile/i18n/es_PY.po
odoo_addons/account_mass_reconcile/i18n/es_VE.po
odoo_addons/account_mass_reconcile/i18n/et.po
odoo_addons/account_mass_reconcile/i18n/eu.po
odoo_addons/account_mass_reconcile/i18n/fa.po
odoo_addons/account_mass_reconcile/i18n/fi.po
odoo_addons/account_mass_reconcile/i18n/fr.po
odoo_addons/account_mass_reconcile/i18n/fr_CA.po
odoo_addons/account_mass_reconcile/i18n/fr_CH.po
odoo_addons/account_mass_reconcile/i18n/fr_FR.po
odoo_addons/account_mass_reconcile/i18n/gl.po
odoo_addons/account_mass_reconcile/i18n/gl_ES.po
odoo_addons/account_mass_reconcile/i18n/he.po
odoo_addons/account_mass_reconcile/i18n/hr.po
odoo9_addon_account_mass_reconcile-9.0.1.0.0.99.dev115.dist-info/METADATA
odoo9_addon_account_mass_reconcile-9.0.1.0.0.99.dev115.dist-info/WHEEL
odoo9_addon_account_mass_reconcile-9.0.1.0.0.99.dev115.dist-info/namespace_packages.txt
odoo9_addon_account_mass_reconcile-9.0.1.0.0.99.dev115.dist-info/top_level.txt
odoo9_addon_account_mass_reconcile-9.0.1.0.0.99.dev115.dist-info/RECORD
